heyoka/__init__.py
heyoka/_ensemble_impl.py
heyoka/_sgp4_test_data.py
heyoka/_sympy_utils.py
heyoka/_test_batch_integrator.py
heyoka/_test_celmec.py
heyoka/_test_cfunc.py
heyoka/_test_dtens.py
heyoka/_test_elp2000.py
heyoka/_test_ensemble.py
heyoka/_test_eop_data.py
heyoka/_test_expression.py
heyoka/_test_lagham.py
heyoka/_test_memcache.py
heyoka/_test_model.py
heyoka/_test_mp.py
heyoka/_test_real.py
heyoka/_test_real128.py
heyoka/_test_scalar_integrator.py
heyoka/_test_sgp4_propagator.py
heyoka/_test_sw_data.py
heyoka/_test_sympy.py
heyoka/_test_var_integrator.py
heyoka/_test_var_ode_sys.py
heyoka/_test_vsop2013.py
heyoka/_version.py
heyoka/core.cpython-312-aarch64-linux-gnu.so
heyoka/test.py
heyoka/callback/__init__.py
heyoka/model/__init__.py
heyoka.libs/libboost_charconv-9e023205.so.1.88.0
heyoka.libs/libboost_regex-992740ea.so.1.88.0
heyoka.libs/libboost_serialization-d18edb1c.so.1.88.0
heyoka.libs/libcrypto-93b77298.so.3
heyoka.libs/libfmt-37df3017.so.12.0.0
heyoka.libs/libgmp-b288de48.so.10.5.0
heyoka.libs/libheyoka-9da44260.so.41.0
heyoka.libs/libmp++-17302cf2.so.16.0
heyoka.libs/libmpfr-7cbfe93f.so.6.2.2
heyoka.libs/libsleef-165ecca7.so.3.9.0
heyoka.libs/libspdlog-98b1f734.so.1.16.0
heyoka.libs/libssl-2b671a00.so.3
heyoka.libs/libtbb-58605295.so.12.17
heyoka-7.9.1.dist-info/METADATA
heyoka-7.9.1.dist-info/WHEEL
heyoka-7.9.1.dist-info/RECORD
heyoka-7.9.1.dist-info/licenses/LICENSE
