Metadata-Version: 2.2
Name: heyoka
Version: 7.9.1
Summary: Python library for ODE integration via Taylor's method and LLVM
Keywords: science,math,physics,ode
Author-Email: Francesco Biscani <bluescarni@gmail.com>
License: MPL-2.0
Classifier: Development Status :: 5 - Production/Stable
Classifier: Operating System :: OS Independent
Classifier: Intended Audience :: Science/Research
Classifier: Topic :: Scientific/Engineering
Classifier: Topic :: Scientific/Engineering :: Mathematics
Classifier: Topic :: Scientific/Engineering :: Physics
Classifier: License :: OSI Approved :: Mozilla Public License 2.0 (MPL 2.0)
Classifier: Programming Language :: Python :: 3
Project-URL: Documentation, https://bluescarni.github.io/heyoka.py/index.html
Project-URL: Repository, https://github.com/bluescarni/heyoka.py
Requires-Python: >=3.9
Requires-Dist: cloudpickle
Requires-Dist: numpy>=2
Requires-Dist: certifi
Provides-Extra: sympy
Requires-Dist: sympy; extra == "sympy"
Requires-Dist: mpmath; extra == "sympy"
Provides-Extra: sgp4
Requires-Dist: skyfield; extra == "sgp4"
